fsman/__init__.py
fsman/_cmdline.py
fsman/cmd.py
fsman/keymap.py
fsman/manager.py
fsspec_manager-0.1.0.dist-info/METADATA
fsspec_manager-0.1.0.dist-info/WHEEL
fsspec_manager-0.1.0.dist-info/RECORD
