Metadata-Version: 2.1
Name: fsspec-manager
Version: 0.1.0
Summary: Curses TUI for fsspec filesystems
License: GPL-3.0-only
Author: Vladislav Wohlrath
Author-email: vladislav@wohlrath.cz
Requires-Python: >=3.9,<4.0
Classifier: License :: OSI Approved :: GNU General Public License v3 (GPLv3)
Classifier: Programming Language :: Python :: 3
Classifier: Programming Language :: Python :: 3.9
Classifier: Programming Language :: Python :: 3.10
Classifier: Programming Language :: Python :: 3.11
Classifier: Programming Language :: Python :: 3.12
Requires-Dist: fsspec (>=2022)
